turkle_client/__init__.py
turkle_client/__version__.py
turkle_client/bin.py
turkle_client/client.py
turkle_client/exceptions.py
turkle_client/monitor.py
turkle_client/schema.py
turkle_client/wrappers.py
turkle_client-0.5.0.dist-info/licenses/LICENSE
turkle_client-0.5.0.dist-info/METADATA
turkle_client-0.5.0.dist-info/WHEEL
turkle_client-0.5.0.dist-info/entry_points.txt
turkle_client-0.5.0.dist-info/top_level.txt
turkle_client-0.5.0.dist-info/RECORD
