Metadata-Version: 2.4
Name: turkle-client
Version: 0.5.0
Summary: Client for the Turkle REST API
Author-email: Cash Costello <cash.costello@gmail.com>
License: BSD
Project-URL: Homepage, https://github.com/hltcoe/turkle-client
Classifier: Development Status :: 4 - Beta
Classifier: Intended Audience :: Developers
Classifier: Topic :: Software Development :: Libraries :: Python Modules
Classifier: Topic :: Scientific/Engineering :: Artificial Intelligence
Classifier: Topic :: Text Processing :: Linguistic
Classifier: License :: OSI Approved :: BSD License
Classifier: Programming Language :: Python :: 3
Classifier: Programming Language :: Python :: 3.7
Classifier: Programming Language :: Python :: 3.8
Classifier: Programming Language :: Python :: 3.9
Classifier: Programming Language :: Python :: 3.10
Classifier: Programming Language :: Python :: 3.11
Classifier: Operating System :: OS Independent
Requires-Python: >=3.7
License-File: LICENSE
Requires-Dist: appdirs
Requires-Dist: requests>=2
Provides-Extra: dev
Requires-Dist: pytest; extra == "dev"
Requires-Dist: vcrpy; extra == "dev"
Requires-Dist: build; extra == "dev"
Requires-Dist: twine; extra == "dev"
Dynamic: license-file
